pde/__init__.py
pde/_version.py
pde/py.typed
pde/backends/__init__.py
pde/backends/base.py
pde/backends/registry.py
pde/backends/numba/__init__.py
pde/backends/numba/_boundaries.py
pde/backends/numba/_solvers.py
pde/backends/numba/backend.py
pde/backends/numba/grids.py
pde/backends/numba/overloads.py
pde/backends/numba/utils.py
pde/backends/numba/operators/__init__.py
pde/backends/numba/operators/cartesian.py
pde/backends/numba/operators/common.py
pde/backends/numba/operators/cylindrical_sym.py
pde/backends/numba/operators/polar_sym.py
pde/backends/numba/operators/spherical_sym.py
pde/backends/numba_mpi/__init__.py
pde/backends/numba_mpi/backend.py
pde/backends/numba_mpi/overloads.py
pde/backends/numpy/__init__.py
pde/backends/numpy/backend.py
pde/backends/scipy/__init__.py
pde/backends/scipy/backend.py
pde/backends/scipy/operators/__init__.py
pde/backends/scipy/operators/cartesian.py
pde/backends/scipy/operators/common.py
pde/backends/scipy/operators/cylindrical_sym.py
pde/backends/scipy/operators/polar_sym.py
pde/backends/scipy/operators/spherical_sym.py
pde/fields/__init__.py
pde/fields/base.py
pde/fields/collection.py
pde/fields/datafield_base.py
pde/fields/scalar.py
pde/fields/tensorial.py
pde/fields/vectorial.py
pde/grids/__init__.py
pde/grids/_mesh.py
pde/grids/base.py
pde/grids/cartesian.py
pde/grids/cylindrical.py
pde/grids/spherical.py
pde/grids/boundaries/__init__.py
pde/grids/boundaries/axes.py
pde/grids/boundaries/axis.py
pde/grids/boundaries/local.py
pde/grids/coordinates/__init__.py
pde/grids/coordinates/base.py
pde/grids/coordinates/bipolar.py
pde/grids/coordinates/bispherical.py
pde/grids/coordinates/cartesian.py
pde/grids/coordinates/cylindrical.py
pde/grids/coordinates/polar.py
pde/grids/coordinates/spherical.py
pde/pdes/__init__.py
pde/pdes/allen_cahn.py
pde/pdes/base.py
pde/pdes/cahn_hilliard.py
pde/pdes/diffusion.py
pde/pdes/kpz_interface.py
pde/pdes/kuramoto_sivashinsky.py
pde/pdes/laplace.py
pde/pdes/pde.py
pde/pdes/swift_hohenberg.py
py_pde-0.50.0.dist-info/licenses/LICENSE
py_pde-0.50.0.dist-info/METADATA
py_pde-0.50.0.dist-info/WHEEL
py_pde-0.50.0.dist-info/top_level.txt
py_pde-0.50.0.dist-info/RECORD
