Metadata-Version: 2.4
Name: py-pde
Version: 0.50.0
Summary: Python package for solving partial differential equations
Author-email: David Zwicker <david.zwicker@ds.mpg.de>
License: MIT
Project-URL: homepage, https://github.com/zwicker-group/py-pde
Project-URL: documentation, http://py-pde.readthedocs.io
Project-URL: repository, https://github.com/zwicker-group/py-pde
Keywords: pdes,partial-differential-equations,dynamical-systems
Classifier: Development Status :: 4 - Beta
Classifier: Intended Audience :: Developers
Classifier: Intended Audience :: Science/Research
Classifier: Topic :: Scientific/Engineering
Classifier: License :: OSI Approved :: MIT License
Classifier: Programming Language :: Python :: 3
Classifier: Programming Language :: Python :: 3.10
Classifier: Programming Language :: Python :: 3.11
Classifier: Programming Language :: Python :: 3.12
Classifier: Programming Language :: Python :: 3.13
Classifier: Programming Language :: Python :: 3.14
Requires-Python: <3.15,>=3.10
License-File: LICENSE
Requires-Dist: matplotlib>=3.1
Requires-Dist: numba>=0.59
Requires-Dist: numpy>=1.22
Requires-Dist: scipy>=1.10
Requires-Dist: sympy>=1.9
Requires-Dist: tqdm>=4.66
Provides-Extra: io
Requires-Dist: h5py>=2.10; extra == "io"
Requires-Dist: pandas>=2; extra == "io"
Requires-Dist: ffmpeg-python>=0.2; extra == "io"
Provides-Extra: interactive
Requires-Dist: napari>=0.4.8; extra == "interactive"
Requires-Dist: ipywidgets>=8; extra == "interactive"
Provides-Extra: mpi
Requires-Dist: numba-mpi>=0.22; extra == "mpi"
Requires-Dist: mpi4py>=3; extra == "mpi"
Dynamic: license-file
